mingk42_lotto/__init__.py
mingk42_lotto/draw.py
mingk42_lotto-0.2.0.dist-info/METADATA
mingk42_lotto-0.2.0.dist-info/WHEEL
mingk42_lotto-0.2.0.dist-info/top_level.txt
mingk42_lotto-0.2.0.dist-info/RECORD
