Metadata-Version: 2.1
Name: mingk42_lotto
Version: 0.2.0
Summary: Default template for PDM package
Author-email: Mingk42 <xoals123456t@gmail.com>
License: MIT
Requires-Python: >=3.9
